mcp_ts/__init__.py
mcp_ts/server.py
mcp_ts-0.1.0.dist-info/METADATA
mcp_ts-0.1.0.dist-info/WHEEL
mcp_ts-0.1.0.dist-info/entry_points.txt
mcp_ts-0.1.0.dist-info/top_level.txt
mcp_ts-0.1.0.dist-info/RECORD
