Metadata-Version: 2.4
Name: mcp-ts
Version: 0.1.0
Summary: 一个简单的MCP加法服务示例
Author-email: CodeBuddy用户 <example@example.com>
License: MIT
Project-URL: Homepage, https://github.com/yourusername/mcp-ts
Project-URL: Bug Tracker, https://github.com/yourusername/mcp-ts/issues
Classifier: Programming Language :: Python :: 3
Classifier: License :: OSI Approved :: MIT License
Classifier: Operating System :: OS Independent
Requires-Python: >=3.8
Requires-Dist: mcp[cli]>=1.13.0
